PySVBench/__init__.py
PySVBench/_baseclasses.py
PySVBench/basetypes.py
PySVBench/generate.py
PySVBench/generators.py
pysvbench-0.6.3.dist-info/licenses/LICENSE
pysvbench-0.6.3.dist-info/METADATA
pysvbench-0.6.3.dist-info/WHEEL
pysvbench-0.6.3.dist-info/top_level.txt
pysvbench-0.6.3.dist-info/RECORD
