Metadata-Version: 2.4
Name: PySVBench
Version: 0.6.3
Home-page: https://github.com/SpaceProgrammerOriginal/PySVBench
Author: SpaceProgrammer
License: Custom
Classifier: License :: Other/Proprietary License
License-File: LICENSE
Dynamic: author
Dynamic: classifier
Dynamic: description
Dynamic: description-content-type
Dynamic: home-page
Dynamic: license
Dynamic: license-file
